pmpl/__init__.py
pmpl/core.py
pmpl/formatters.py
pmpl/styles.py
pmpl-0.1.1.dist-info/METADATA
pmpl-0.1.1.dist-info/WHEEL
pmpl-0.1.1.dist-info/licenses/LICENSE
pmpl-0.1.1.dist-info/RECORD
