Metadata-Version: 2.4
Name: pmpl
Version: 0.1.1
Summary: Pretty Matplotlib - Create presentation-ready plots with minimal effort
Project-URL: Homepage, https://github.com/RensterMaat/pmpl
Project-URL: Documentation, https://pmpl.readthedocs.io
Project-URL: Repository, https://github.com/RensterMaat/pmpl
Project-URL: Issues, https://github.com/RensterMaat/pmpl/issues
Project-URL: Changelog, https://github.com/RensterMaat/pmpl/blob/main/CHANGELOG.md
Author-email: Rens ter Maat <rens.termaat@gmail.com>
License: MIT
License-File: LICENSE
Keywords: matplotlib,plotting,presentation,styling,visualization
Classifier: Development Status :: 3 - Alpha
Classifier: Intended Audience :: Developers
Classifier: Intended Audience :: Science/Research
Classifier: License :: OSI Approved :: MIT License
Classifier: Programming Language :: Python :: 3
Classifier: Programming Language :: Python :: 3.12
Classifier: Topic :: Scientific/Engineering :: Visualization
Classifier: Typing :: Typed
Requires-Python: >=3.12
Requires-Dist: matplotlib>=3.10.8
Requires-Dist: numpy>=2.3.5
Provides-Extra: dev
Requires-Dist: hatchling>=1.28.0; extra == 'dev'
Requires-Dist: ipykernel>=7.1.0; extra == 'dev'
Requires-Dist: jupyter>=1.1.1; extra == 'dev'
Requires-Dist: pre-commit>=4.5.0; extra == 'dev'
Requires-Dist: python-semantic-release>=10.5.2; extra == 'dev'
Requires-Dist: ruff>=0.14.9; extra == 'dev'
Provides-Extra: docs
Requires-Dist: myst-parser>=4.0.1; extra == 'docs'
Requires-Dist: sphinx-autodoc-typehints>=3.5.2; extra == 'docs'
Requires-Dist: sphinx-rtd-theme>=3.0.2; extra == 'docs'
Requires-Dist: sphinx>=8.2.3; extra == 'docs'
Provides-Extra: test
Requires-Dist: pytest-cov>=7.0.0; extra == 'test'
Requires-Dist: pytest>=9.0.2; extra == 'test'
